rapidb/__init__.py
rapidb-0.7.0.dist-info/METADATA
rapidb-0.7.0.dist-info/WHEEL
rapidb-0.7.0.dist-info/top_level.txt
rapidb-0.7.0.dist-info/RECORD
